pt_pump_up_admin/CRUD.py
pt_pump_up_admin/PT_Pump_Up_Admin.py
pt_pump_up_admin/__init__.py
pt_pump_up_admin/author/Author.py
pt_pump_up_admin/author/__init__.py
pt_pump_up_admin/dataset/Dataset.py
pt_pump_up_admin/dataset/__init__.py
pt_pump_up_admin/link/Link.py
pt_pump_up_admin/link/__init__.py
pt_pump_up_admin/model/Model.py
pt_pump_up_admin/model/__init__.py
pt_pump_up_admin/nlp_task/NLP_Task.py
pt_pump_up_admin/nlp_task/__init__.py
pt_pump_up_admin/resource_stats/ResourceStats.py
pt_pump_up_admin/resource_stats/__init__.py
pt_pump_up_admin/result/Result.py
pt_pump_up_admin/result/__init__.py
pt_pump_up_admin-0.0.4.dist-info/METADATA
pt_pump_up_admin-0.0.4.dist-info/WHEEL
pt_pump_up_admin-0.0.4.dist-info/top_level.txt
pt_pump_up_admin-0.0.4.dist-info/RECORD
